django_textchunks-0.1.1.dist-info/METADATA
django_textchunks-0.1.1.dist-info/top_level.txt
django_textchunks-0.1.1.dist-info/RECORD
django_textchunks-0.1.1.dist-info/DESCRIPTION.rst
django_textchunks-0.1.1.dist-info/metadata.json
django_textchunks-0.1.1.dist-info/WHEEL
textchunks/forms.py
textchunks/__init__.py
textchunks/models.py
textchunks/admin.py
textchunks/templates/textchunks/plain.html
textchunks/templatetags/__init__.py
textchunks/templatetags/textchunks.py
textchunks/migrations/__init__.py
textchunks/migrations/0001_initial.py
