Metadata-Version: 2.0
Name: django-textchunks
Version: 0.1.1
Summary: Keyed blocks of text or html content for use in your Django templates
Home-page: https://github.com/aleosd/django-textchukns
Author: aleosd
Author-email: osdalex@gmail.com
License: UNKNOWN
Keywords: django text chunks templates
Platform: UNKNOWN
Classifier: Development Status :: 5 - Production/Stable
Classifier: Environment :: Web Environment
Classifier: Framework :: Django
Classifier: Intended Audience :: Developers
Classifier: Operating System :: OS Independent
Classifier: Programming Language :: Python
Classifier: License :: OSI Approved :: BSD License
Classifier: Topic :: Utilities
